{
  "db_name": "PostgreSQL",
  "query": "UPDATE\n                    storage_providers\n               SET\n                    next_url_discovery_at = NOW() + INTERVAL '1 second' * $2,\n                    updated_at = NOW()\n               WHERE\n                    provider_id = $1\n            ",
  "describe": {
    "columns": [],
    "parameters": {
      "Left": [
        "Text",
        "Float8"
      ]
    },
    "nullable": []
  },
  "hash": "25b3ae24b12a0bc03e47e33aac153a4b4377a6f1230340a11da7ab957ad1f521"
}
